meeseeksbox/.__init__.py.swp
meeseeksbox/.__init__.py.un~
meeseeksbox/.core.py.un~
meeseeksbox/.scopes.py.un~
meeseeksbox/.utils.py.swp
meeseeksbox/.utils.py.un~
meeseeksbox/__init__.py
meeseeksbox/commands.py
meeseeksbox/core.py
meeseeksbox/scopes.py
meeseeksbox/utils.py
meeseeksbox-0.0.4.dist-info/WHEEL
meeseeksbox-0.0.4.dist-info/METADATA
meeseeksbox-0.0.4.dist-info/RECORD
