Metadata-Version: 1.2
Name: meeseeksbox
Version: 0.0.4
Summary: MeeseeksBox
Home-page: https://github.com/Carreau/meeseeksbox
License: UNKNOWN
Author: Matthias Bussonnier
Author-email: bussonniermatthias@gmail.com
Requires-Python: >=3.4
Classifier: License :: OSI Approved :: MIT License
Requires-Dist: tornado
Requires-Dist: requests
Requires-Dist: pyjwt
Requires-Dist: gitpython
Requires-Dist: there
Requires-Dist: mock
Requires-Dist: cryptography
Requires-Dist: friendlyautopep8
Requires-Dist: yieldbreaker
